flespi_sdk/__init__.py
flespi_sdk/cli.py
flespi_sdk/exception.py
flespi_sdk/base/__init__.py
flespi_sdk/base/flespi_session.py
flespi_sdk/base/item.py
flespi_sdk/base/items.py
flespi_sdk/modules/__init__.py
flespi_sdk/modules/devices/__init__.py
flespi_sdk/modules/devices/device.py
flespi_sdk/modules/mqtt/__init__.py
flespi_sdk/modules/realms/__init__.py
flespi_sdk/modules/realms/realm.py
flespi_sdk/modules/realms/realm_home.py
flespi_sdk/modules/realms/realm_token_params.py
flespi_sdk/modules/realms/users/__init__.py
flespi_sdk/modules/realms/users/user.py
flespi_sdk/modules/subaccounts/__init__.py
flespi_sdk/modules/subaccounts/account.py
flespi_sdk-0.2.1.dist-info/METADATA
flespi_sdk-0.2.1.dist-info/WHEEL
flespi_sdk-0.2.1.dist-info/RECORD
