Metadata-Version: 2.4
Name: flespi-sdk
Version: 0.2.1
Summary: Add your description here
Author-email: Sergey Shevchik <sergey.shevchik@gmail.com>
Requires-Python: >=3.11
Requires-Dist: aiohttp>=3.11.15
